{
  "associatedLayout": "Testin room",
  "name": "Player_Main_Weapon_Core",
  "events": [
    {
      "colorB": 228,
      "colorG": 176,
      "colorR": 74,
      "creationTime": 0,
      "name": "Player MAIN - WEAPON CORE (OPTIMIZED)",
      "source": "",
      "type": "BuiltinCommonInstructions::Group",
      "events": [
        {
          "type": "BuiltinCommonInstructions::Comment",
          "color": {
            "b": 0,
            "g": 0,
            "r": 0,
            "textB": 0,
            "textG": 0,
            "textR": 0
          },
          "comment": "INIT"
        },
        {
          "type": "BuiltinCommonInstructions::Standard",
          "conditions": [
            {
              "type": {
                "value": "SceneJustBegins"
              },
              "parameters": [
                ""
              ]
            }
          ],
          "actions": [
            {
              "type": {
                "value": "SetNumberVariable"
              },
              "parameters": [
                "CurrentWeaponId",
                "=",
                "0"
              ]
            },
            {
              "type": {
                "value": "SetNumberVariable"
              },
              "parameters": [
                "LastWeaponId",
                "=",
                "-1"
              ]
            },
            {
              "type": {
                "value": "SetNumberVariable"
              },
              "parameters": [
                "NextShootAt",
                "=",
                "0"
              ]
            },
            {
              "type": {
                "value": "SetNumberVariable"
              },
              "parameters": [
                "WeaponDamage",
                "=",
                "1"
              ]
            },
            {
              "type": {
                "value": "SetNumberVariable"
              },
              "parameters": [
                "WeaponFireDelay",
                "=",
                "0.14"
              ]
            },
            {
              "type": {
                "value": "SetNumberVariable"
              },
              "parameters": [
                "WeaponBulletSpeed",
                "=",
                "300"
              ]
            },
            {
              "type": {
                "value": "SetNumberVariable"
              },
              "parameters": [
                "WeaponAmmoCost",
                "=",
                "1"
              ]
            },
            {
              "type": {
                "value": "SetStringVariable"
              },
              "parameters": [
                "WeaponShootAnim",
                "=",
                "\"Shoot_Pistol\""
              ]
            },
            {
              "type": {
                "value": "Create"
              },
              "parameters": [
                "",
                "GunRevolver",
                "Player.PointX(\"GunHand\")",
                "Player.PointY(\"GunHand\")",
                ""
              ]
            },
            {
              "type": {
                "value": "Create"
              },
              "parameters": [
                "",
                "GunShotgun",
                "Player.PointX(\"GunHand\")",
                "Player.PointY(\"GunHand\")",
                ""
              ]
            },
            {
              "type": {
                "value": "Create"
              },
              "parameters": [
                "",
                "GunRifle",
                "Player.PointX(\"GunHand\")",
                "Player.PointY(\"GunHand\")",
                ""
              ]
            },
            {
              "type": {
                "value": "Create"
              },
              "parameters": [
                "",
                "GunRay",
                "Player.PointX(\"GunHand\")",
                "Player.PointY(\"GunHand\")",
                ""
              ]
            }
          ]
        },
        {
          "type": "BuiltinCommonInstructions::Comment",
          "color": {
            "b": 0,
            "g": 0,
            "r": 0,
            "textB": 0,
            "textG": 0,
            "textR": 0
          },
          "comment": "WEAPON SWITCH"
        },
        {
          "type": "BuiltinCommonInstructions::Standard",
          "conditions": [
            {
              "type": {
                "value": "KeyFromTextPressed"
              },
              "parameters": [
                "",
                "\"Num1\""
              ]
            }
          ],
          "actions": [
            {
              "type": {
                "value": "SetNumberVariable"
              },
              "parameters": [
                "CurrentWeaponId",
                "=",
                "0"
              ]
            }
          ]
        },
        {
          "type": "BuiltinCommonInstructions::Standard",
          "conditions": [
            {
              "type": {
                "value": "KeyFromTextPressed"
              },
              "parameters": [
                "",
                "\"Num2\""
              ]
            }
          ],
          "actions": [
            {
              "type": {
                "value": "SetNumberVariable"
              },
              "parameters": [
                "CurrentWeaponId",
                "=",
                "1"
              ]
            }
          ]
        },
        {
          "type": "BuiltinCommonInstructions::Standard",
          "conditions": [
            {
              "type": {
                "value": "KeyFromTextPressed"
              },
              "parameters": [
                "",
                "\"Num3\""
              ]
            }
          ],
          "actions": [
            {
              "type": {
                "value": "SetNumberVariable"
              },
              "parameters": [
                "CurrentWeaponId",
                "=",
                "2"
              ]
            }
          ]
        },
        {
          "type": "BuiltinCommonInstructions::Standard",
          "conditions": [
            {
              "type": {
                "value": "KeyFromTextPressed"
              },
              "parameters": [
                "",
                "\"Num4\""
              ]
            }
          ],
          "actions": [
            {
              "type": {
                "value": "SetNumberVariable"
              },
              "parameters": [
                "CurrentWeaponId",
                "=",
                "3"
              ]
            }
          ]
        },
        {
          "type": "BuiltinCommonInstructions::Comment",
          "color": {
            "b": 0,
            "g": 0,
            "r": 0,
            "textB": 0,
            "textG": 0,
            "textR": 0
          },
          "comment": "EQUIP PROFILE (TRIGGERED ON CHANGE)"
        },
        {
          "type": "BuiltinCommonInstructions::Standard",
          "conditions": [
            {
              "type": {
                "value": "NumberVariable"
              },
              "parameters": [
                "CurrentWeaponId",
                "!=",
                "LastWeaponId"
              ]
            },
            {
              "type": {
                "value": "NumberVariable"
              },
              "parameters": [
                "CurrentWeaponId",
                "=",
                "0"
              ]
            }
          ],
          "actions": [
            {
              "type": {
                "value": "SetNumberVariable"
              },
              "parameters": [
                "LastWeaponId",
                "=",
                "0"
              ]
            },
            {
              "type": {
                "value": "SetNumberVariable"
              },
              "parameters": [
                "WeaponDamage",
                "=",
                "1"
              ]
            },
            {
              "type": {
                "value": "SetNumberVariable"
              },
              "parameters": [
                "WeaponFireDelay",
                "=",
                "0.14"
              ]
            },
            {
              "type": {
                "value": "SetNumberVariable"
              },
              "parameters": [
                "WeaponBulletSpeed",
                "=",
                "300"
              ]
            },
            {
              "type": {
                "value": "SetNumberVariable"
              },
              "parameters": [
                "WeaponAmmoCost",
                "=",
                "1"
              ]
            },
            {
              "type": {
                "value": "SetStringVariable"
              },
              "parameters": [
                "WeaponShootAnim",
                "=",
                "\"Shoot_Pistol\""
              ]
            },
            {
              "type": {
                "value": "SetNumberVariable"
              },
              "parameters": [
                "WeaponMag",
                "=",
                "5"
              ]
            },
            {
              "type": {
                "value": "Show"
              },
              "parameters": [
                "GunRevolver"
              ]
            },
            {
              "type": {
                "value": "Hide"
              },
              "parameters": [
                "GunShotgun"
              ]
            },
            {
              "type": {
                "value": "Hide"
              },
              "parameters": [
                "GunRifle"
              ]
            },
            {
              "type": {
                "value": "Hide"
              },
              "parameters": [
                "GunRay"
              ]
            }
          ]
        },
        {
          "type": "BuiltinCommonInstructions::Standard",
          "conditions": [
            {
              "type": {
                "value": "NumberVariable"
              },
              "parameters": [
                "CurrentWeaponId",
                "!=",
                "LastWeaponId"
              ]
            },
            {
              "type": {
                "value": "NumberVariable"
              },
              "parameters": [
                "CurrentWeaponId",
                "=",
                "1"
              ]
            }
          ],
          "actions": [
            {
              "type": {
                "value": "SetNumberVariable"
              },
              "parameters": [
                "LastWeaponId",
                "=",
                "1"
              ]
            },
            {
              "type": {
                "value": "SetNumberVariable"
              },
              "parameters": [
                "WeaponDamage",
                "=",
                "2"
              ]
            },
            {
              "type": {
                "value": "SetNumberVariable"
              },
              "parameters": [
                "WeaponFireDelay",
                "=",
                "0.45"
              ]
            },
            {
              "type": {
                "value": "SetNumberVariable"
              },
              "parameters": [
                "WeaponBulletSpeed",
                "=",
                "240"
              ]
            },
            {
              "type": {
                "value": "SetNumberVariable"
              },
              "parameters": [
                "WeaponAmmoCost",
                "=",
                "1"
              ]
            },
            {
              "type": {
                "value": "SetStringVariable"
              },
              "parameters": [
                "WeaponShootAnim",
                "=",
                "\"Shoot_Shotgun\""
              ]
            },
            {
              "type": {
                "value": "SetNumberVariable"
              },
              "parameters": [
                "WeaponMag",
                "=",
                "9"
              ]
            },
            {
              "type": {
                "value": "Hide"
              },
              "parameters": [
                "GunRevolver"
              ]
            },
            {
              "type": {
                "value": "Show"
              },
              "parameters": [
                "GunShotgun"
              ]
            },
            {
              "type": {
                "value": "Hide"
              },
              "parameters": [
                "GunRifle"
              ]
            },
            {
              "type": {
                "value": "Hide"
              },
              "parameters": [
                "GunRay"
              ]
            }
          ]
        },
        {
          "type": "BuiltinCommonInstructions::Standard",
          "conditions": [
            {
              "type": {
                "value": "NumberVariable"
              },
              "parameters": [
                "CurrentWeaponId",
                "!=",
                "LastWeaponId"
              ]
            },
            {
              "type": {
                "value": "NumberVariable"
              },
              "parameters": [
                "CurrentWeaponId",
                "=",
                "2"
              ]
            }
          ],
          "actions": [
            {
              "type": {
                "value": "SetNumberVariable"
              },
              "parameters": [
                "LastWeaponId",
                "=",
                "2"
              ]
            },
            {
              "type": {
                "value": "SetNumberVariable"
              },
              "parameters": [
                "WeaponDamage",
                "=",
                "1"
              ]
            },
            {
              "type": {
                "value": "SetNumberVariable"
              },
              "parameters": [
                "WeaponFireDelay",
                "=",
                "0.08"
              ]
            },
            {
              "type": {
                "value": "SetNumberVariable"
              },
              "parameters": [
                "WeaponBulletSpeed",
                "=",
                "360"
              ]
            },
            {
              "type": {
                "value": "SetNumberVariable"
              },
              "parameters": [
                "WeaponAmmoCost",
                "=",
                "1"
              ]
            },
            {
              "type": {
                "value": "SetStringVariable"
              },
              "parameters": [
                "WeaponShootAnim",
                "=",
                "\"Shoot_Rifle\""
              ]
            },
            {
              "type": {
                "value": "SetNumberVariable"
              },
              "parameters": [
                "WeaponMag",
                "=",
                "10"
              ]
            },
            {
              "type": {
                "value": "Hide"
              },
              "parameters": [
                "GunRevolver"
              ]
            },
            {
              "type": {
                "value": "Hide"
              },
              "parameters": [
                "GunShotgun"
              ]
            },
            {
              "type": {
                "value": "Show"
              },
              "parameters": [
                "GunRifle"
              ]
            },
            {
              "type": {
                "value": "Hide"
              },
              "parameters": [
                "GunRay"
              ]
            }
          ]
        },
        {
          "type": "BuiltinCommonInstructions::Standard",
          "conditions": [
            {
              "type": {
                "value": "NumberVariable"
              },
              "parameters": [
                "CurrentWeaponId",
                "!=",
                "LastWeaponId"
              ]
            },
            {
              "type": {
                "value": "NumberVariable"
              },
              "parameters": [
                "CurrentWeaponId",
                "=",
                "3"
              ]
            }
          ],
          "actions": [
            {
              "type": {
                "value": "SetNumberVariable"
              },
              "parameters": [
                "LastWeaponId",
                "=",
                "3"
              ]
            },
            {
              "type": {
                "value": "SetNumberVariable"
              },
              "parameters": [
                "WeaponDamage",
                "=",
                "2"
              ]
            },
            {
              "type": {
                "value": "SetNumberVariable"
              },
              "parameters": [
                "WeaponFireDelay",
                "=",
                "0.1"
              ]
            },
            {
              "type": {
                "value": "SetNumberVariable"
              },
              "parameters": [
                "WeaponBulletSpeed",
                "=",
                "540"
              ]
            },
            {
              "type": {
                "value": "SetNumberVariable"
              },
              "parameters": [
                "WeaponAmmoCost",
                "=",
                "2"
              ]
            },
            {
              "type": {
                "value": "SetStringVariable"
              },
              "parameters": [
                "WeaponShootAnim",
                "=",
                "\"Shoot_Ray\""
              ]
            },
            {
              "type": {
                "value": "SetNumberVariable"
              },
              "parameters": [
                "WeaponMag",
                "=",
                "6"
              ]
            },
            {
              "type": {
                "value": "Hide"
              },
              "parameters": [
                "GunRevolver"
              ]
            },
            {
              "type": {
                "value": "Hide"
              },
              "parameters": [
                "GunShotgun"
              ]
            },
            {
              "type": {
                "value": "Hide"
              },
              "parameters": [
                "GunRifle"
              ]
            },
            {
              "type": {
                "value": "Show"
              },
              "parameters": [
                "GunRay"
              ]
            }
          ]
        },
        {
          "type": "BuiltinCommonInstructions::Comment",
          "color": {
            "b": 0,
            "g": 0,
            "r": 0,
            "textB": 0,
            "textG": 0,
            "textR": 0
          },
          "comment": "FOLLOW + AIM + FLIP (VISIBLE ONLY)"
        },
        {
          "type": "BuiltinCommonInstructions::Standard",
          "conditions": [
            {
              "type": {
                "value": "Visible"
              },
              "parameters": [
                "GunRevolver"
              ]
            }
          ],
          "actions": [
            {
              "type": {
                "value": "SetXY"
              },
              "parameters": [
                "GunRevolver",
                "=",
                "Player.PointX(\"GunHand\")",
                "=",
                "Player.PointY(\"GunHand\")"
              ]
            },
            {
              "type": {
                "value": "RotateTowardPosition"
              },
              "parameters": [
                "GunRevolver",
                "Player.PointX(\"GunAim\")",
                "Player.PointY(\"GunAim\")",
                "0",
                ""
              ]
            }
          ],
          "events": [
            {
              "type": "BuiltinCommonInstructions::Standard",
              "conditions": [
                {
                  "type": {
                    "value": "FlippableCapability::FlippableBehavior::FlippedX"
                  },
                  "parameters": [
                    "Player",
                    "Flippable"
                  ]
                }
              ],
              "actions": [
                {
                  "type": {
                    "value": "FlippableCapability::FlippableBehavior::FlipX"
                  },
                  "parameters": [
                    "GunRevolver",
                    "Flippable",
                    "no"
                  ]
                },
                {
                  "type": {
                    "value": "FlippableCapability::FlippableBehavior::FlipY"
                  },
                  "parameters": [
                    "GunRevolver",
                    "Flippable",
                    "no"
                  ]
                }
              ]
            },
            {
              "type": "BuiltinCommonInstructions::Standard",
              "conditions": [
                {
                  "type": {
                    "inverted": true,
                    "value": "FlippableCapability::FlippableBehavior::FlippedX"
                  },
                  "parameters": [
                    "Player",
                    "Flippable"
                  ]
                }
              ],
              "actions": [
                {
                  "type": {
                    "value": "FlippableCapability::FlippableBehavior::FlipX"
                  },
                  "parameters": [
                    "GunRevolver",
                    "Flippable",
                    ""
                  ]
                },
                {
                  "type": {
                    "value": "FlippableCapability::FlippableBehavior::FlipY"
                  },
                  "parameters": [
                    "GunRevolver",
                    "Flippable",
                    "no"
                  ]
                }
              ]
            }
          ]
        },
        {
          "type": "BuiltinCommonInstructions::Standard",
          "conditions": [
            {
              "type": {
                "value": "Visible"
              },
              "parameters": [
                "GunShotgun"
              ]
            }
          ],
          "actions": [
            {
              "type": {
                "value": "SetXY"
              },
              "parameters": [
                "GunShotgun",
                "=",
                "Player.PointX(\"GunHand\")",
                "=",
                "Player.PointY(\"GunHand\")"
              ]
            },
            {
              "type": {
                "value": "RotateTowardPosition"
              },
              "parameters": [
                "GunShotgun",
                "Player.PointX(\"GunAim\")",
                "Player.PointY(\"GunAim\")",
                "0",
                ""
              ]
            }
          ],
          "events": [
            {
              "type": "BuiltinCommonInstructions::Standard",
              "conditions": [
                {
                  "type": {
                    "value": "FlippableCapability::FlippableBehavior::FlippedX"
                  },
                  "parameters": [
                    "Player",
                    "Flippable"
                  ]
                }
              ],
              "actions": [
                {
                  "type": {
                    "value": "FlippableCapability::FlippableBehavior::FlipX"
                  },
                  "parameters": [
                    "GunShotgun",
                    "Flippable",
                    "yes"
                  ]
                }
              ]
            },
            {
              "type": "BuiltinCommonInstructions::Standard",
              "conditions": [
                {
                  "type": {
                    "inverted": true,
                    "value": "FlippableCapability::FlippableBehavior::FlippedX"
                  },
                  "parameters": [
                    "Player",
                    "Flippable"
                  ]
                }
              ],
              "actions": [
                {
                  "type": {
                    "value": "FlippableCapability::FlippableBehavior::FlipX"
                  },
                  "parameters": [
                    "GunShotgun",
                    "Flippable",
                    ""
                  ]
                }
              ]
            }
          ]
        },
        {
          "type": "BuiltinCommonInstructions::Standard",
          "conditions": [
            {
              "type": {
                "value": "Visible"
              },
              "parameters": [
                "GunRifle"
              ]
            }
          ],
          "actions": [
            {
              "type": {
                "value": "SetXY"
              },
              "parameters": [
                "GunRifle",
                "=",
                "Player.PointX(\"GunHand\")",
                "=",
                "Player.PointY(\"GunHand\")"
              ]
            },
            {
              "type": {
                "value": "RotateTowardPosition"
              },
              "parameters": [
                "GunRifle",
                "Player.PointX(\"GunAim\")",
                "Player.PointY(\"GunAim\")",
                "0",
                ""
              ]
            }
          ],
          "events": [
            {
              "type": "BuiltinCommonInstructions::Standard",
              "conditions": [
                {
                  "type": {
                    "value": "FlippableCapability::FlippableBehavior::FlippedX"
                  },
                  "parameters": [
                    "Player",
                    "Flippable"
                  ]
                }
              ],
              "actions": [
                {
                  "type": {
                    "value": "FlippableCapability::FlippableBehavior::FlipX"
                  },
                  "parameters": [
                    "GunRifle",
                    "Flippable",
                    "yes"
                  ]
                }
              ]
            },
            {
              "type": "BuiltinCommonInstructions::Standard",
              "conditions": [
                {
                  "type": {
                    "inverted": true,
                    "value": "FlippableCapability::FlippableBehavior::FlippedX"
                  },
                  "parameters": [
                    "Player",
                    "Flippable"
                  ]
                }
              ],
              "actions": [
                {
                  "type": {
                    "value": "FlippableCapability::FlippableBehavior::FlipX"
                  },
                  "parameters": [
                    "GunRifle",
                    "Flippable",
                    ""
                  ]
                }
              ]
            }
          ]
        },
        {
          "type": "BuiltinCommonInstructions::Standard",
          "conditions": [
            {
              "type": {
                "value": "Visible"
              },
              "parameters": [
                "GunRay"
              ]
            }
          ],
          "actions": [
            {
              "type": {
                "value": "SetXY"
              },
              "parameters": [
                "GunRay",
                "=",
                "Player.PointX(\"GunHand\")",
                "=",
                "Player.PointY(\"GunHand\")"
              ]
            },
            {
              "type": {
                "value": "RotateTowardPosition"
              },
              "parameters": [
                "GunRay",
                "Player.PointX(\"GunAim\")",
                "Player.PointY(\"GunAim\")",
                "0",
                ""
              ]
            }
          ],
          "events": [
            {
              "type": "BuiltinCommonInstructions::Standard",
              "conditions": [
                {
                  "type": {
                    "value": "FlippableCapability::FlippableBehavior::FlippedX"
                  },
                  "parameters": [
                    "Player",
                    "Flippable"
                  ]
                }
              ],
              "actions": [
                {
                  "type": {
                    "value": "FlippableCapability::FlippableBehavior::FlipX"
                  },
                  "parameters": [
                    "GunRay",
                    "Flippable",
                    "yes"
                  ]
                }
              ]
            },
            {
              "type": "BuiltinCommonInstructions::Standard",
              "conditions": [
                {
                  "type": {
                    "inverted": true,
                    "value": "FlippableCapability::FlippableBehavior::FlippedX"
                  },
                  "parameters": [
                    "Player",
                    "Flippable"
                  ]
                }
              ],
              "actions": [
                {
                  "type": {
                    "value": "FlippableCapability::FlippableBehavior::FlipX"
                  },
                  "parameters": [
                    "GunRay",
                    "Flippable",
                    ""
                  ]
                }
              ]
            }
          ]
        },
        {
          "type": "BuiltinCommonInstructions::Comment",
          "color": {
            "b": 0,
            "g": 0,
            "r": 0,
            "textB": 0,
            "textG": 0,
            "textR": 0
          },
          "comment": "GLOBAL SHOOT ROUTER (Optimized)"
        },
        {
          "type": "BuiltinCommonInstructions::Standard",
          "conditions": [
            {
              "type": {
                "value": "KeyPressed"
              },
              "parameters": [
                "",
                "v"
              ]
            },
            {
              "type": {
                "value": "NumberVariable"
              },
              "parameters": [
                "CanControl",
                "=",
                "1"
              ]
            },
            {
              "type": {
                "value": "NumberVariable"
              },
              "parameters": [
                "State",
                "!=",
                "6"
              ]
            },
            {
              "type": {
                "value": "NumberVariable"
              },
              "parameters": [
                "State",
                "!=",
                "9"
              ]
            },
            {
              "type": {
                "value": "NumberVariable"
              },
              "parameters": [
                "State",
                "!=",
                "11"
              ]
            },
            {
              "type": {
                "value": "NumberVariable"
              },
              "parameters": [
                "NextShootAt",
                "<=",
                "TimeFromStart()"
              ]
            },
            {
              "type": {
                "value": "NumberObjectVariable"
              },
              "parameters": [
                "Player",
                "GunBulletCounter",
                "<",
                "6"
              ]
            },
            {
              "type": {
                "value": "NumberVariable"
              },
              "parameters": [
                "TextForGunAmmunition",
                ">",
                "0"
              ]
            },
            {
              "type": {
                "value": "BooleanObjectVariable"
              },
              "parameters": [
                "Player",
                "isShooting",
                "False",
                ""
              ]
            }
          ],
          "actions": [
            {
              "type": {
                "value": "SetBooleanObjectVariable"
              },
              "parameters": [
                "Player",
                "isShooting",
                "True",
                ""
              ]
            },
            {
              "type": {
                "value": "SetNumberVariable"
              },
              "parameters": [
                "NextShootAt",
                "=",
                "TimeFromStart()+WeaponFireDelay"
              ]
            },
            {
              "type": {
                "value": "SetNumberVariable"
              },
              "parameters": [
                "State",
                "=",
                "12"
              ]
            }
          ]
        },
        {
          "type": "BuiltinCommonInstructions::Standard",
          "conditions": [
            {
              "type": {
                "value": "KeyPressed"
              },
              "parameters": [
                "",
                "v"
              ]
            },
            {
              "type": {
                "value": "NumberVariable"
              },
              "parameters": [
                "CanControl",
                "=",
                "1"
              ]
            },
            {
              "type": {
                "value": "NumberVariable"
              },
              "parameters": [
                "State",
                "!=",
                "6"
              ]
            },
            {
              "type": {
                "value": "NumberVariable"
              },
              "parameters": [
                "State",
                "!=",
                "9"
              ]
            },
            {
              "type": {
                "value": "NumberVariable"
              },
              "parameters": [
                "State",
                "!=",
                "11"
              ]
            },
            {
              "type": {
                "value": "NumberVariable"
              },
              "parameters": [
                "NextShootAt",
                "<=",
                "TimeFromStart()"
              ]
            },
            {
              "type": {
                "value": "NumberObjectVariable"
              },
              "parameters": [
                "Player",
                "GunBulletCounter",
                "<",
                "6"
              ]
            },
            {
              "type": {
                "value": "NumberVariable"
              },
              "parameters": [
                "TextForGunAmmunition",
                ">",
                "0"
              ]
            },
            {
              "type": {
                "value": "BooleanObjectVariable"
              },
              "parameters": [
                "Player",
                "isShooting",
                "False",
                ""
              ]
            },
            {
              "type": {
                "value": "PlatformBehavior::IsOnFloor"
              },
              "parameters": [
                "Player",
                "PlatformerObject"
              ]
            },
            {
              "type": {
                "value": "PlatformBehavior::PlatformerObjectBehavior::IsMovingEvenALittle"
              },
              "parameters": [
                "Player",
                "PlatformerObject"
              ]
            }
          ],
          "actions": [
            {
              "type": {
                "value": "SetBooleanObjectVariable"
              },
              "parameters": [
                "Player",
                "isShooting",
                "True",
                ""
              ]
            },
            {
              "type": {
                "value": "SetNumberVariable"
              },
              "parameters": [
                "NextShootAt",
                "=",
                "TimeFromStart()+WeaponFireDelay"
              ]
            },
            {
              "type": {
                "value": "SetNumberVariable"
              },
              "parameters": [
                "State",
                "=",
                "8"
              ]
            }
          ]
        }
      ],
      "parameters": []
    }
  ]
}
